<?xml version="1.0" encoding="UTF-8"?><indexer gendate="2023-03-05T14:43:51"><layer name="Semesterübergreifend" dirName="Semester+C3+BCbergreifend"><layer name="Android" dirName="Android" duration="2:01:26" videoCount="7"><video xmlns:xsi="http://www.w3.org/2001/XMLSchema-instance" author="plass" date="2014-02-19" duration="13:27" id="455" pubdate="2014-02-19" title="1. Erste Schritte mit Android" url="http://mediathek.mt.haw-hamburg.de/video/1-Erste-Schritte-mit-Android/764a47d37b371d53552ce0ec7cb799c6"><file type="mp4" url="http://mediathek.mt.haw-hamburg.de/getMedium/764a47d37b371d53552ce0ec7cb799c6.mp4"/><file type="webm" url="http://mediathek.mt.haw-hamburg.de/getMedium/764a47d37b371d53552ce0ec7cb799c6.webm"/></video><video xmlns:xsi="http://www.w3.org/2001/XMLSchema-instance" author="plass" date="2014-02-19" duration="08:30" id="496" pubdate="2014-02-19" title="2. Android Tutorials, Hilfe, Referenzen" url="http://mediathek.mt.haw-hamburg.de/video/2-Android-Tutorials-Hilfe-Referenzen/cc54e312db756f66b6570c634bed07fe"><file type="mp4" url="http://mediathek.mt.haw-hamburg.de/getMedium/cc54e312db756f66b6570c634bed07fe.mp4"/><file type="webm" url="http://mediathek.mt.haw-hamburg.de/getMedium/cc54e312db756f66b6570c634bed07fe.webm"/></video><video xmlns:xsi="http://www.w3.org/2001/XMLSchema-instance" author="plass" date="2014-02-19" duration="09:01" id="499" pubdate="2014-02-19" title="3. Android Debugging und Devices" url="http://mediathek.mt.haw-hamburg.de/video/3-Android-Debugging-und-Devices/0a0f05a40c924c9ef576ce14cbeb5e4e"><file type="mp4" url="http://mediathek.mt.haw-hamburg.de/getMedium/0a0f05a40c924c9ef576ce14cbeb5e4e.mp4"/><file type="webm" url="http://mediathek.mt.haw-hamburg.de/getMedium/0a0f05a40c924c9ef576ce14cbeb5e4e.webm"/></video><video xmlns:xsi="http://www.w3.org/2001/XMLSchema-instance" author="plass" date="2014-02-19" duration="16:26" id="497" pubdate="2014-02-19" title="4. Android: Controls und Eventhandling" url="http://mediathek.mt.haw-hamburg.de/video/4-Android-Controls-und-Eventhandling/5183abe04d7e80dbfc4d1ee80d914562"><file type="mp4" url="http://mediathek.mt.haw-hamburg.de/getMedium/5183abe04d7e80dbfc4d1ee80d914562.mp4"/><file type="webm" url="http://mediathek.mt.haw-hamburg.de/getMedium/5183abe04d7e80dbfc4d1ee80d914562.webm"/></video><video xmlns:xsi="http://www.w3.org/2001/XMLSchema-instance" author="plass" date="2014-02-19" duration="22:29" id="498" pubdate="2014-02-19" title="5. Android: Activities und Intents" url="http://mediathek.mt.haw-hamburg.de/video/5-Android-Activities-und-Intents/c07c4d6d7b48bf3950a5c6fdfdd441eb"><file type="mp4" url="http://mediathek.mt.haw-hamburg.de/getMedium/c07c4d6d7b48bf3950a5c6fdfdd441eb.mp4"/><file type="webm" url="http://mediathek.mt.haw-hamburg.de/getMedium/c07c4d6d7b48bf3950a5c6fdfdd441eb.webm"/></video><video xmlns:xsi="http://www.w3.org/2001/XMLSchema-instance" author="plass" date="2014-02-19" duration="32:14" id="500" pubdate="2014-02-19" title="6. Android: List Views" url="http://mediathek.mt.haw-hamburg.de/video/6-Android-List-Views/fd0ffa85087afa837230b5c2f26413a6"><file type="mp4" url="http://mediathek.mt.haw-hamburg.de/getMedium/fd0ffa85087afa837230b5c2f26413a6.mp4"/><file type="webm" url="http://mediathek.mt.haw-hamburg.de/getMedium/fd0ffa85087afa837230b5c2f26413a6.webm"/></video><video xmlns:xsi="http://www.w3.org/2001/XMLSchema-instance" author="plass" date="2014-02-19" duration="19:19" id="487" pubdate="2014-02-19" title="7. Android: Actionbar" url="http://mediathek.mt.haw-hamburg.de/video/7-Android-Actionbar/17b728e146271bc454fb2a87568127a1"><file type="mp4" url="http://mediathek.mt.haw-hamburg.de/getMedium/17b728e146271bc454fb2a87568127a1.mp4"/><file type="webm" url="http://mediathek.mt.haw-hamburg.de/getMedium/17b728e146271bc454fb2a87568127a1.webm"/></video></layer><layer name="Dies und das" dirName="Dies_und_das"><layer name="2013-12-20" dirName="2013-12-20" duration="40:11" comments="2" videoCount="2"><video xmlns:xsi="http://www.w3.org/2001/XMLSchema-instance" author="Weitz" comments="1" date="2013-12-20" duration="19:53" id="1108" pubdate="2013-12-21" title="DD 2013-12-20 01 Weihnachtsvorlesung - Satz von Pick (extended remix)" url="http://mediathek.mt.haw-hamburg.de/video/DD-2013-12-20-01-Weihnachtsvorlesung-Satz-von-Pick-extended-remix/ae363578e2d77ffbbdc1b61a93eabc88"><file type="mp4" url="http://mediathek.mt.haw-hamburg.de/getMedium/ae363578e2d77ffbbdc1b61a93eabc88.mp4"/><file type="webm" url="http://mediathek.mt.haw-hamburg.de/getMedium/ae363578e2d77ffbbdc1b61a93eabc88.webm"/></video><video xmlns:xsi="http://www.w3.org/2001/XMLSchema-instance" author="Weitz" comments="1" date="2013-12-20" duration="20:18" id="1107" pubdate="2013-12-21" title="DD 2013-12-20 02 Weihnachtsvorlesung - Goodstein-Folgen (extended remix)" url="http://mediathek.mt.haw-hamburg.de/video/DD-2013-12-20-02-Weihnachtsvorlesung-Goodstein-Folgen-extended-remix/ea00280605d45b310cfb2066097fa627"><file type="mp4" url="http://mediathek.mt.haw-hamburg.de/getMedium/ea00280605d45b310cfb2066097fa627.mp4"/><file type="webm" url="http://mediathek.mt.haw-hamburg.de/getMedium/ea00280605d45b310cfb2066097fa627.webm"/></video></layer><layer name="2014-05-02" dirName="2014-05-02" duration="49:42" comments="2" videoCount="3"><video xmlns:xsi="http://www.w3.org/2001/XMLSchema-instance" author="Weitz" comments="1" date="2014-05-02" duration="37:29" id="811" pubdate="2014-05-06" title="DD 2014-05-02 01 Friese und ihre Symmetrien" url="http://mediathek.mt.haw-hamburg.de/video/DD-2014-05-02-01-Friese-und-ihre-Symmetrien/1ed8f2acb3223991b1645f06ba50e076"><file type="mp4" url="http://mediathek.mt.haw-hamburg.de/getMedium/1ed8f2acb3223991b1645f06ba50e076.mp4"/><file type="webm" url="http://mediathek.mt.haw-hamburg.de/getMedium/1ed8f2acb3223991b1645f06ba50e076.webm"/></video><video xmlns:xsi="http://www.w3.org/2001/XMLSchema-instance" author="Weitz" date="2014-05-02" duration="07:38" id="810" pubdate="2014-05-06" title="DD 2014-05-02 02 Parkettierungen" url="http://mediathek.mt.haw-hamburg.de/video/DD-2014-05-02-02-Parkettierungen/ddf26ba3567c8aca41d5d499f114d0d9"><file type="mp4" url="http://mediathek.mt.haw-hamburg.de/getMedium/ddf26ba3567c8aca41d5d499f114d0d9.mp4"/><file type="webm" url="http://mediathek.mt.haw-hamburg.de/getMedium/ddf26ba3567c8aca41d5d499f114d0d9.webm"/></video><video xmlns:xsi="http://www.w3.org/2001/XMLSchema-instance" author="Weitz" comments="1" date="2014-05-02" duration="04:35" id="812" pubdate="2014-05-06" title="DD 2014-05-02 03 Häuser bauen" url="http://mediathek.mt.haw-hamburg.de/video/DD-2014-05-02-03-Haeuser-bauen/9b92b4344499960f83664ee5adb38759"><file type="mp4" url="http://mediathek.mt.haw-hamburg.de/getMedium/9b92b4344499960f83664ee5adb38759.mp4"/><file type="webm" url="http://mediathek.mt.haw-hamburg.de/getMedium/9b92b4344499960f83664ee5adb38759.webm"/></video></layer><layer name="2014-05-30" dirName="2014-05-30" duration="1:01:53" videoCount="1"><video xmlns:xsi="http://www.w3.org/2001/XMLSchema-instance" author="Weitz" date="2014-05-30" duration="1:01:53" id="869" pubdate="2014-05-28" title="DD 2014-05-30 01 Der Vier-Farben-Satz" url="http://mediathek.mt.haw-hamburg.de/video/DD-2014-05-30-01-Der-Vier-Farben-Satz/9e01efef3f275d309a948bbcd8ad9903"><file type="mp4" url="http://mediathek.mt.haw-hamburg.de/getMedium/9e01efef3f275d309a948bbcd8ad9903.mp4"/><file type="webm" url="http://mediathek.mt.haw-hamburg.de/getMedium/9e01efef3f275d309a948bbcd8ad9903.webm"/></video></layer><layer name="2014-06-20" dirName="2014-06-20" duration="16:40" videoCount="1"><video xmlns:xsi="http://www.w3.org/2001/XMLSchema-instance" author="Weitz" date="2014-06-20" duration="16:40" id="961" pubdate="2014-06-21" title="DD 2014-06-20 01 Das Buffonsche Nadelproblem" url="http://mediathek.mt.haw-hamburg.de/video/DD-2014-06-20-01-Das-Buffonsche-Nadelproblem/6cf23088e6a23675629ae726644e7fc8"><file type="mp4" url="http://mediathek.mt.haw-hamburg.de/getMedium/6cf23088e6a23675629ae726644e7fc8.mp4"/><file type="webm" url="http://mediathek.mt.haw-hamburg.de/getMedium/6cf23088e6a23675629ae726644e7fc8.webm"/></video></layer><layer name="2014-12-17" dirName="2014-12-17" duration="2:42:31" comments="2" videoCount="3"><video xmlns:xsi="http://www.w3.org/2001/XMLSchema-instance" author="Weitz" comments="1" date="2014-12-17" duration="1:18:09" id="1279" pubdate="2014-12-27" title="DD 2014-12-17 01 Weihnachtsvorlesung - Polygone" url="http://mediathek.mt.haw-hamburg.de/video/DD-2014-12-17-01-Weihnachtsvorlesung-Polygone/1791ed9ce1b6965f84fc08782da24665"><file type="mp4" url="http://mediathek.mt.haw-hamburg.de/getMedium/1791ed9ce1b6965f84fc08782da24665.mp4"/><file type="webm" url="http://mediathek.mt.haw-hamburg.de/getMedium/1791ed9ce1b6965f84fc08782da24665.webm"/></video><video xmlns:xsi="http://www.w3.org/2001/XMLSchema-instance" author="Weitz" date="2014-12-17" duration="26:19" id="1278" pubdate="2014-12-27" title="DD 2014-12-17 02 Nachtrag Weihnachtsvorlesung - Innen oder außen?" url="http://mediathek.mt.haw-hamburg.de/video/DD-2014-12-17-02-Nachtrag-Weihnachtsvorlesung-Innen-oder-aussen/87905b68d8747af7f995caf6345b73fd"><file type="mp4" url="http://mediathek.mt.haw-hamburg.de/getMedium/87905b68d8747af7f995caf6345b73fd.mp4"/><file type="webm" url="http://mediathek.mt.haw-hamburg.de/getMedium/87905b68d8747af7f995caf6345b73fd.webm"/></video><video xmlns:xsi="http://www.w3.org/2001/XMLSchema-instance" author="Weitz" comments="1" date="2014-12-17" duration="58:03" id="1280" pubdate="2014-12-27" title="DD 2014-12-17 03 Nachtrag Weihnachtsvorlesung - Hilberts drittes Problem" url="http://mediathek.mt.haw-hamburg.de/video/DD-2014-12-17-03-Nachtrag-Weihnachtsvorlesung-Hilberts-drittes-Problem/024d3da9faa1cd3004de645f15e32199"><file type="mp4" url="http://mediathek.mt.haw-hamburg.de/getMedium/024d3da9faa1cd3004de645f15e32199.mp4"/><file type="webm" url="http://mediathek.mt.haw-hamburg.de/getMedium/024d3da9faa1cd3004de645f15e32199.webm"/></video></layer><layer name="2015-03-16" dirName="2015-03-16" duration="1:12:44" videoCount="2"><video xmlns:xsi="http://www.w3.org/2001/XMLSchema-instance" author="Weitz" date="2015-03-16" duration="36:22" id="1302" pubdate="2015-03-15" title="DD 2015-03-16 01 Pythagoräische Tripel" url="http://mediathek.mt.haw-hamburg.de/video/DD-2015-03-16-01-Pythagoraeische-Tripel/9a5af197856b78e9bfa62b5bb5b8c47f"><file type="mp4" url="http://mediathek.mt.haw-hamburg.de/getMedium/9a5af197856b78e9bfa62b5bb5b8c47f.mp4"/></video><video xmlns:xsi="http://www.w3.org/2001/XMLSchema-instance" author="Weitz" date="2015-03-16" duration="36:22" id="1301" pubdate="2015-03-15" title="DD 2015-03-16 Pythagoräische Tripel" url="http://mediathek.mt.haw-hamburg.de/video/DD-2015-03-16-Pythagoraeische-Tripel/9a5af197856b78e9bfa62b5bb5b8c47f"><file type="mp4" url="http://mediathek.mt.haw-hamburg.de/images/media/9a5af197856b78e9bfa62b5bb5b8c47f_1426454620.mp4"/></video></layer><layer name="2015-04-13" dirName="2015-04-13" duration="40:34" videoCount="1"><video xmlns:xsi="http://www.w3.org/2001/XMLSchema-instance" author="Weitz" date="2015-04-13" duration="40:34" id="1317" pubdate="2015-04-12" title="DD 2015-04-13 01 Berechnung von Wochentagen" url="http://mediathek.mt.haw-hamburg.de/video/DD-2015-04-13-01-Berechnung-von-Wochentagen/2181436d187c7fca4b0fd922100b94f2"><file type="mp4" url="http://mediathek.mt.haw-hamburg.de/getMedium/2181436d187c7fca4b0fd922100b94f2.mp4"/></video></layer><layer name="2015-12-16" dirName="2015-12-16" duration="1:10:52" comments="2" videoCount="1"><video xmlns:xsi="http://www.w3.org/2001/XMLSchema-instance" author="Weitz" comments="2" date="2015-12-16" duration="1:10:52" id="1363" pubdate="2015-12-16" title="DD 2015-12-16 01 Weihnachtsvorlesung - Vier Probleme" url="http://mediathek.mt.haw-hamburg.de/video/DD-2015-12-16-01-Weihnachtsvorlesung-Vier-Probleme/3eef2ec03630b047a94f99045d552afc"><file type="mp4" url="http://mediathek.mt.haw-hamburg.de/getMedium/3eef2ec03630b047a94f99045d552afc.mp4"/></video></layer><layer name="2016-10-10" dirName="2016-10-10" duration="1:15:19" comments="2" videoCount="1"><video xmlns:xsi="http://www.w3.org/2001/XMLSchema-instance" author="Weitz" comments="2" date="2016-10-10" duration="1:15:19" id="1439" pubdate="2016-10-10" title="DD 2016-10-10 01 Algorithmen" url="http://mediathek.mt.haw-hamburg.de/video/DD-2016-10-10-01-Algorithmen/c85d16720ff5796742c3992e0472669c"><file type="mp4" url="http://mediathek.mt.haw-hamburg.de/getMedium/c85d16720ff5796742c3992e0472669c.mp4"/></video></layer><layer name="2016-12-19" dirName="2016-12-19" duration="1:44:48" comments="1" videoCount="1"><video xmlns:xsi="http://www.w3.org/2001/XMLSchema-instance" author="Weitz" comments="1" date="2016-12-19" duration="1:44:48" id="1523" pubdate="2016-12-19" title="DD 2016-12-19 01 Weihnachtsvorlesung - Die Riemannsche Vermutung" url="http://mediathek.mt.haw-hamburg.de/video/DD-2016-12-19-01-Weihnachtsvorlesung-Die-Riemannsche-Vermutung/ca401b3b86b39e8ab141285a57049c56"><file type="mp4" url="http://mediathek.mt.haw-hamburg.de/getMedium/ca401b3b86b39e8ab141285a57049c56.mp4"/></video></layer><layer name="2017-08-27" dirName="2017-08-27" duration="24:27" comments="1" videoCount="1"><video xmlns:xsi="http://www.w3.org/2001/XMLSchema-instance" author="Weitz" comments="1" date="2017-08-27" duration="24:27" id="1887" pubdate="2018-08-17" title="DD 2017-08-27 01 Typische LaTeX-Fehler und wie man sie vermeidet" url="http://mediathek.mt.haw-hamburg.de/video/DD-2017-08-27-01-Typische-LaTeX-Fehler-und-wie-man-sie-vermeidet/78938fd9f06a3add55077e4e7065ed80"><file type="mp4" url="http://mediathek.mt.haw-hamburg.de/getMedium/78938fd9f06a3add55077e4e7065ed80.mp4"/></video></layer><layer name="2017-09-03" dirName="2017-09-03" duration="37:08" videoCount="1"><video xmlns:xsi="http://www.w3.org/2001/XMLSchema-instance" author="Weitz" date="2017-09-03" duration="37:08" id="1886" pubdate="2018-08-17" title="DD 2017-09-03 01 Das regelmäßige 17-Eck und andere Konstruktionen mit Zirkel und Lineal" url="http://mediathek.mt.haw-hamburg.de/video/DD-2017-09-03-01-Das-regelmaessige-17-Eck-und-andere-Konstruktionen-mit-Zirkel-und-Lineal/d8248916de42e6dc6a365632f9b9dbf0"><file type="mp4" url="http://mediathek.mt.haw-hamburg.de/getMedium/d8248916de42e6dc6a365632f9b9dbf0.mp4"/></video></layer><layer name="2017-09-08" dirName="2017-09-08" duration="16:25" comments="1" videoCount="1"><video xmlns:xsi="http://www.w3.org/2001/XMLSchema-instance" author="Weitz" comments="1" date="2017-09-08" duration="16:25" id="1885" pubdate="2018-08-17" title="DD 2017-09-08 01 Computer sind zu dumm für Tetris oder: Die Rolle der Intuition in der Mathematik" url="http://mediathek.mt.haw-hamburg.de/video/DD-2017-09-08-01-Computer-sind-zu-dumm-fuer-Tetris-oder-Die-Rolle-der-Intuition-in-der-Mathematik/61b1f00ff0a53015c11c6620226d6561"><file type="mp4" url="http://mediathek.mt.haw-hamburg.de/getMedium/61b1f00ff0a53015c11c6620226d6561.mp4"/></video></layer><layer name="2017-09-18" dirName="2017-09-18" duration="35:22" comments="1" videoCount="1"><video xmlns:xsi="http://www.w3.org/2001/XMLSchema-instance" author="Weitz" comments="1" date="2017-09-18" duration="35:22" id="1900" pubdate="2018-08-31" title="DD 2017-09-18 01 Der goldene Schnitt und die Fibonacci-Folge" url="http://mediathek.mt.haw-hamburg.de/video/DD-2017-09-18-01-Der-goldene-Schnitt-und-die-Fibonacci-Folge/e4c3a62c43f486a88468a33ad2c245bf"><file type="mp4" url="http://mediathek.mt.haw-hamburg.de/getMedium/e4c3a62c43f486a88468a33ad2c245bf.mp4"/></video></layer><layer name="2017-09-23" dirName="2017-09-23" duration="26:08" comments="1" videoCount="1"><video xmlns:xsi="http://www.w3.org/2001/XMLSchema-instance" author="Weitz" comments="1" date="2017-09-23" duration="26:08" id="1884" pubdate="2018-08-17" title="DD 2017-09-23 01 Ägyptische Brüche (und zwei ungelöste mathematische Probleme)" url="http://mediathek.mt.haw-hamburg.de/video/DD-2017-09-23-01-Aegyptische-Brueche-und-zwei-ungeloeste-mathematische-Probleme/30585d218351c8364e5b892d3d5e4b3c"><file type="mp4" url="http://mediathek.mt.haw-hamburg.de/getMedium/30585d218351c8364e5b892d3d5e4b3c.mp4"/></video></layer><layer name="2017-10-26" dirName="2017-10-26" duration="10:34" videoCount="1"><video xmlns:xsi="http://www.w3.org/2001/XMLSchema-instance" author="Weitz" date="2017-10-26" duration="10:34" id="1892" pubdate="2018-08-30" title="DD 2017-10-26 01 Ist eins eine Primzahl? Ist null eine natürliche Zahl?" url="http://mediathek.mt.haw-hamburg.de/video/DD-2017-10-26-01-Ist-eins-eine-Primzahl-Ist-null-eine-natuerliche-Zahl/0290d9141778417c9eb7716cdad63076"><file type="mp4" url="http://mediathek.mt.haw-hamburg.de/getMedium/0290d9141778417c9eb7716cdad63076.mp4"/></video></layer><layer name="2017-10-29" dirName="2017-10-29" duration="47:57" comments="1" videoCount="1"><video xmlns:xsi="http://www.w3.org/2001/XMLSchema-instance" author="Weitz" comments="1" date="2017-10-29" duration="47:57" id="1897" pubdate="2018-08-30" title="DD 2017-10-29 01 Was ist Nichtstandardanalysis? Was sind hyperreelle Zahlen?" url="http://mediathek.mt.haw-hamburg.de/video/DD-2017-10-29-01-Was-ist-Nichtstandardanalysis-Was-sind-hyperreelle-Zahlen/031d614d7c26984fd6e9969dbf53273e"><file type="mp4" url="http://mediathek.mt.haw-hamburg.de/getMedium/031d614d7c26984fd6e9969dbf53273e.mp4"/></video></layer><layer name="2017-12-19" dirName="2017-12-19" duration="2:11:49" comments="3" videoCount="4"><video xmlns:xsi="http://www.w3.org/2001/XMLSchema-instance" author="Weitz" comments="1" date="2017-12-19" duration="46:39" id="1896" pubdate="2018-08-30" title="DD 2017-12-19 01 Was Mathematiker NICHT können (Weihnachtsvorlesung 2017, Teil 1 von 4)" url="http://mediathek.mt.haw-hamburg.de/video/DD-2017-12-19-01-Was-Mathematiker-NICHT-koennen-Weihnachtsvorlesung-2017-Teil-1-von-4/c03d8441758900cb7744cbb19752063a"><file type="mp4" url="http://mediathek.mt.haw-hamburg.de/getMedium/c03d8441758900cb7744cbb19752063a.mp4"/></video><video xmlns:xsi="http://www.w3.org/2001/XMLSchema-instance" author="Weitz" comments="1" date="2017-12-19" duration="34:24" id="1894" pubdate="2018-08-30" title="DD 2017-12-19 02 Gleichungen, die nicht lösbar sind (Weihnachtsvorlesung 2017, Teil 2 von 4)" url="http://mediathek.mt.haw-hamburg.de/video/DD-2017-12-19-02-Gleichungen-die-nicht-loesbar-sind-Weihnachtsvorlesung-2017-Teil-2-von-4/0c72a91308d14533c600f1920e3010db"><file type="mp4" url="http://mediathek.mt.haw-hamburg.de/getMedium/0c72a91308d14533c600f1920e3010db.mp4"/></video><video xmlns:xsi="http://www.w3.org/2001/XMLSchema-instance" author="Weitz" date="2017-12-19" duration="24:50" id="1898" pubdate="2018-08-30" title="DD 2017-12-19 03 Nicht-euklidische Geometrien (Weihnachtsvorlesung 2017, Teil 3 von 4)" url="http://mediathek.mt.haw-hamburg.de/video/DD-2017-12-19-03-Nicht-euklidische-Geometrien-Weihnachtsvorlesung-2017-Teil-3-von-4/63a3e044f3992408b3e2fef858d70aac"><file type="mp4" url="http://mediathek.mt.haw-hamburg.de/getMedium/63a3e044f3992408b3e2fef858d70aac.mp4"/></video><video xmlns:xsi="http://www.w3.org/2001/XMLSchema-instance" author="Weitz" comments="1" date="2017-12-19" duration="25:56" id="1895" pubdate="2018-08-30" title="DD 2017-12-19 04 Gödels Unvollständigkeitssätze und die Kontinuumshypothese (Weihnachtsvorlesung 2017, Teil 4 von 4)" url="http://mediathek.mt.haw-hamburg.de/video/DD-2017-12-19-04-Goedels-Unvollstaendigkeitssaetze-und-die-Kontinuumshypothese-Weihnachtsvorlesung-2017-Teil-4-von-4/c41872adba10d78ff7ae9bcb5f1dbf36"><file type="mp4" url="http://mediathek.mt.haw-hamburg.de/getMedium/c41872adba10d78ff7ae9bcb5f1dbf36.mp4"/></video></layer><layer name="2018-01-28" dirName="2018-01-28" duration="24:38" comments="1" videoCount="1"><video xmlns:xsi="http://www.w3.org/2001/XMLSchema-instance" author="Weitz" comments="1" date="2018-01-28" duration="24:38" id="1901" pubdate="2018-08-31" title="DD 2018-01-28 01 Der Gitterpunktsatz von Minkowski" url="http://mediathek.mt.haw-hamburg.de/video/DD-2018-01-28-01-Der-Gitterpunktsatz-von-Minkowski/53da380b13c4a30ae1fa2d31f5866452"><file type="mp4" url="http://mediathek.mt.haw-hamburg.de/getMedium/53da380b13c4a30ae1fa2d31f5866452.mp4"/></video></layer><layer name="2018-02-13" dirName="2018-02-13" duration="51:03" comments="1" videoCount="1"><video xmlns:xsi="http://www.w3.org/2001/XMLSchema-instance" author="Weitz" comments="1" date="2018-02-13" duration="51:03" id="1899" pubdate="2018-08-31" title="DD 2018-02-13 01 Was hat Pi mit den Primzahlen zu tun?" url="http://mediathek.mt.haw-hamburg.de/video/DD-2018-02-13-01-Was-hat-Pi-mit-den-Primzahlen-zu-tun/ed08fff734c590c16f6c06bc0fe8db46"><file type="mp4" url="http://mediathek.mt.haw-hamburg.de/getMedium/ed08fff734c590c16f6c06bc0fe8db46.mp4"/></video></layer><layer name="2018-08-26" dirName="2018-08-26" duration="45:27" videoCount="1"><video xmlns:xsi="http://www.w3.org/2001/XMLSchema-instance" author="Weitz" date="2018-08-26" duration="45:27" id="1890" pubdate="2018-08-26" title="DD 2018-08-26 01 Warum man manche Funktionen nicht integrieren kann" url="http://mediathek.mt.haw-hamburg.de/video/DD-2018-08-26-01-Warum-man-manche-Funktionen-nicht-integrieren-kann/aa9ab4c71b8b657a3d861cdbaa402d62"><file type="mp4" url="http://mediathek.mt.haw-hamburg.de/getMedium/aa9ab4c71b8b657a3d861cdbaa402d62.mp4"/></video></layer><layer name="2018-08-29" dirName="2018-08-29" duration="52:24" videoCount="1"><video xmlns:xsi="http://www.w3.org/2001/XMLSchema-instance" author="Weitz" date="2018-08-29" duration="52:24" id="1893" pubdate="2018-08-30" title="DD 2018-08-29 01 Das Zermelo-Fraenkel-Axiomensystem der Mengenlehre (ZF)" url="http://mediathek.mt.haw-hamburg.de/video/DD-2018-08-29-01-Das-Zermelo-Fraenkel-Axiomensystem-der-Mengenlehre-ZF/18c7d12afbae099b0810bc4b2943432b"><file type="mp4" url="http://mediathek.mt.haw-hamburg.de/getMedium/18c7d12afbae099b0810bc4b2943432b.mp4"/></video></layer><layer name="2018-09-09" dirName="2018-09-09" duration="34:10" videoCount="1"><video xmlns:xsi="http://www.w3.org/2001/XMLSchema-instance" author="Weitz" date="2018-09-09" duration="34:10" id="1902" pubdate="2018-09-09" title="DD 2018-09-09 01 Das (berühmt-berüchtigte) Auswahlaxiom" url="http://mediathek.mt.haw-hamburg.de/video/DD-2018-09-09-01-Das-beruehmt-beruechtigte-Auswahlaxiom/e8c3f1c5bc2ea968c8fc187baa3d639c"><file type="mp4" url="http://mediathek.mt.haw-hamburg.de/getMedium/e8c3f1c5bc2ea968c8fc187baa3d639c.mp4"/></video></layer><layer name="2018-10-13" dirName="2018-10-13" duration="27:14" videoCount="1"><video xmlns:xsi="http://www.w3.org/2001/XMLSchema-instance" author="Weitz" date="2018-10-13" duration="27:14" id="1905" pubdate="2018-10-14" title="DD 2018-10-13 01 Interpolation durch natürliche kubische Splines" url="http://mediathek.mt.haw-hamburg.de/video/DD-2018-10-13-01-Interpolation-durch-natuerliche-kubische-Splines/08350fd032c92a9e7935f9d010a1dc76"><file type="mp4" url="http://mediathek.mt.haw-hamburg.de/getMedium/08350fd032c92a9e7935f9d010a1dc76.mp4"/></video></layer><layer name="2018-10-15" dirName="2018-10-15" duration="34:08" videoCount="1"><video xmlns:xsi="http://www.w3.org/2001/XMLSchema-instance" author="Weitz" date="2018-10-15" duration="34:08" id="1906" pubdate="2018-10-15" title="DD 2018-10-15 01 Der Hobby-Algorithmus für &quot;schöne&quot; Kurven" url="http://mediathek.mt.haw-hamburg.de/video/DD-2018-10-15-01-Der-Hobby-Algorithmus-fuer-quotschoenequot-Kurven/511045e9344da4637f41a58eedbe24bb"><file type="mp4" url="http://mediathek.mt.haw-hamburg.de/getMedium/511045e9344da4637f41a58eedbe24bb.mp4"/></video></layer><layer name="2018-11-05" dirName="2018-11-05" duration="11:10" videoCount="1"><video xmlns:xsi="http://www.w3.org/2001/XMLSchema-instance" author="Weitz" date="2018-11-05" duration="11:10" id="1922" pubdate="2018-11-05" title="DD 2018-11-05 01 Knobelaufgabe: Gleichseitige Dreiecke" url="http://mediathek.mt.haw-hamburg.de/video/DD-2018-11-05-01-Knobelaufgabe-Gleichseitige-Dreiecke/c6fa413db33d2bca00995f27e4e09a42"><file type="mp4" url="http://mediathek.mt.haw-hamburg.de/getMedium/c6fa413db33d2bca00995f27e4e09a42.mp4"/></video></layer><layer name="2018-12-18" dirName="2018-12-18" duration="1:59:12" videoCount="3"><video xmlns:xsi="http://www.w3.org/2001/XMLSchema-instance" author="Weitz" date="2018-12-18" duration="49:17" id="1930" pubdate="2018-12-18" title="DD 2018-12-18 01 Die Poincaré-Vermutung (Teil 1, Weihnachtsvorlesung 2018)" url="http://mediathek.mt.haw-hamburg.de/video/DD-2018-12-18-01-Die-Poincare-Vermutung-Teil-1-Weihnachtsvorlesung-2018/92c0099896deac5cdccda343d16e259a"><file type="mp4" url="http://mediathek.mt.haw-hamburg.de/getMedium/92c0099896deac5cdccda343d16e259a.mp4"/></video><video xmlns:xsi="http://www.w3.org/2001/XMLSchema-instance" author="Weitz" date="2018-12-18" duration="31:45" id="1932" pubdate="2018-12-19" title="DD 2018-12-18 02 Die Poincaré-Vermutung (Teil 2, Weihnachtsvorlesung 2018)" url="http://mediathek.mt.haw-hamburg.de/video/DD-2018-12-18-02-Die-Poincare-Vermutung-Teil-2-Weihnachtsvorlesung-2018/537bdcee6a216bab7c049cde0950ba4a"><file type="mp4" url="http://mediathek.mt.haw-hamburg.de/getMedium/537bdcee6a216bab7c049cde0950ba4a.mp4"/></video><video xmlns:xsi="http://www.w3.org/2001/XMLSchema-instance" author="Weitz" date="2018-12-18" duration="38:10" id="1933" pubdate="2018-12-19" title="DD 2018-12-18 03 Die Poincaré-Vermutung (Teil 3, Weihnachtsvorlesung 2018)" url="http://mediathek.mt.haw-hamburg.de/video/DD-2018-12-18-03-Die-Poincare-Vermutung-Teil-3-Weihnachtsvorlesung-2018/b820398f4721be3a1b3b29c357d42593"><file type="mp4" url="http://mediathek.mt.haw-hamburg.de/getMedium/b820398f4721be3a1b3b29c357d42593.mp4"/></video></layer><layer name="2019-02-08" dirName="2019-02-08" duration="52:47" videoCount="2"><video xmlns:xsi="http://www.w3.org/2001/XMLSchema-instance" author="Weitz" date="2019-02-08" duration="26:06" id="1938" pubdate="2019-02-08" title="DD 2019-02-08 01 Überraschende Wahrscheinlichkeiten: ein unfaires Münzspiel" url="http://mediathek.mt.haw-hamburg.de/video/DD-2019-02-08-01-Ueberraschende-Wahrscheinlichkeiten-ein-unfaires-Muenzspiel/0011a4fff4d4e7bf064541089c5b3e76"><file type="mp4" url="http://mediathek.mt.haw-hamburg.de/getMedium/0011a4fff4d4e7bf064541089c5b3e76.mp4"/></video><video xmlns:xsi="http://www.w3.org/2001/XMLSchema-instance" author="Weitz" date="2019-02-08" duration="26:41" id="1939" pubdate="2019-02-09" title="DD 2019-02-08 01 Überraschende Wahrscheinlichkeiten: ein unfaires Münzspiel" url="http://mediathek.mt.haw-hamburg.de/video/DD-2019-02-08-01-Ueberraschende-Wahrscheinlichkeiten-ein-unfaires-Muenzspiel/1c019a5bc26ef7c8eecd5cea4041ab02"><file type="mp4" url="http://mediathek.mt.haw-hamburg.de/getMedium/1c019a5bc26ef7c8eecd5cea4041ab02.mp4"/></video></layer><layer name="2019-12-19" dirName="2019-12-19" duration="1:53:48" videoCount="2"><video xmlns:xsi="http://www.w3.org/2001/XMLSchema-instance" author="Weitz" date="2019-12-19" duration="59:18" id="2079" pubdate="2019-12-20" title="DD 2019-12-19 01 Die Keplersche Vermutung (Weihnachtsvorlesung 2019, Teil 1 von 2)" url="http://mediathek.mt.haw-hamburg.de/video/DD-2019-12-19-01-Die-Keplersche-Vermutung-Weihnachtsvorlesung-2019-Teil-1-von-2/101ba0ebd62f5e425b83039ac54f94ab"><file type="mp4" url="http://mediathek.mt.haw-hamburg.de/getMedium/101ba0ebd62f5e425b83039ac54f94ab.mp4"/></video><video xmlns:xsi="http://www.w3.org/2001/XMLSchema-instance" author="Weitz" date="2019-12-19" duration="54:30" id="2080" pubdate="2019-12-21" title="DD 2019-12-19 02 Die Keplersche Vermutung (Weihnachtsvorlesung 2019, Teil 2 von 2)" url="http://mediathek.mt.haw-hamburg.de/video/DD-2019-12-19-02-Die-Keplersche-Vermutung-Weihnachtsvorlesung-2019-Teil-2-von-2/21be6f0eaed12c3e92f6533e703e2383"><file type="mp4" url="http://mediathek.mt.haw-hamburg.de/getMedium/21be6f0eaed12c3e92f6533e703e2383.mp4"/></video></layer><layer name="2020-02-09" dirName="2020-02-09" duration="29:32" videoCount="1"><video xmlns:xsi="http://www.w3.org/2001/XMLSchema-instance" author="Weitz" date="2020-02-09" duration="29:32" id="2081" pubdate="2020-02-09" title="DD 2020-02-09 01 Mathematik-Meditation: 99 Schnittpunkte" url="http://mediathek.mt.haw-hamburg.de/video/DD-2020-02-09-01-Mathematik-Meditation-99-Schnittpunkte/303f931e666c9bcf45e93decf44a5953"><file type="mp4" url="http://mediathek.mt.haw-hamburg.de/getMedium/303f931e666c9bcf45e93decf44a5953.mp4"/></video></layer><layer name="2020-02-23" dirName="2020-02-23" duration="05:07" videoCount="1"><video xmlns:xsi="http://www.w3.org/2001/XMLSchema-instance" author="Weitz" date="2020-02-23" duration="05:07" id="2082" pubdate="2020-02-23" title="DD 2020-02-23 01 XR Graph - Kurven und Flächen in Virtual und Augmented Reality" url="http://mediathek.mt.haw-hamburg.de/video/DD-2020-02-23-01-XR-Graph-Kurven-und-Flaechen-in-Virtual-und-Augmented-Reality/1c18cee7981654314dd9cb09e1b5312b"><file type="mp4" url="http://mediathek.mt.haw-hamburg.de/getMedium/1c18cee7981654314dd9cb09e1b5312b.mp4"/></video></layer><layer name="2020-03-18" dirName="2020-03-18" duration="21:59" videoCount="1"><video xmlns:xsi="http://www.w3.org/2001/XMLSchema-instance" author="Weitz" date="2020-03-18" duration="21:59" id="2084" pubdate="2020-03-18" title="DD 2020-03-18 01 Mathematik in Zeiten von Corona: Was ist exponentielles Wachstum?" url="http://mediathek.mt.haw-hamburg.de/video/DD-2020-03-18-01-Mathematik-in-Zeiten-von-Corona-Was-ist-exponentielles-Wachstum/38b00ba77b4dbe901348191a554035ee"><file type="mp4" url="http://mediathek.mt.haw-hamburg.de/getMedium/38b00ba77b4dbe901348191a554035ee.mp4"/></video></layer><layer name="2020-03-23" dirName="2020-03-23" duration="57:20" videoCount="2"><video xmlns:xsi="http://www.w3.org/2001/XMLSchema-instance" author="Weitz" date="2020-03-23" duration="28:40" id="2085" pubdate="2020-03-24" title="DD 2020-03-23 01 Was ist eigentlich Mathematik? (Fermats Windflügel)" url="http://mediathek.mt.haw-hamburg.de/video/DD-2020-03-23-01-Was-ist-eigentlich-Mathematik-Fermats-Windfluegel/98d83cef89d8f81185f776b42f72ed1d"><file type="mp4" url="http://mediathek.mt.haw-hamburg.de/getMedium/98d83cef89d8f81185f776b42f72ed1d.mp4"/></video><video xmlns:xsi="http://www.w3.org/2001/XMLSchema-instance" author="Weitz" date="2020-03-23" duration="28:40" id="2088" pubdate="2020-03-24" title="DD 2020-03-23 01 Was ist eigentlich Mathematik? (Fermats Windmühlen)" url="http://mediathek.mt.haw-hamburg.de/video/DD-2020-03-23-01-Was-ist-eigentlich-Mathematik-Fermats-Windmuehlen/98d83cef89d8f81185f776b42f72ed1d"><file type="mp4" url="http://mediathek.mt.haw-hamburg.de/getMedium/98d83cef89d8f81185f776b42f72ed1d.mp4"/></video></layer><layer name="2020-03-29" dirName="2020-03-29" duration="30:31" videoCount="1"><video xmlns:xsi="http://www.w3.org/2001/XMLSchema-instance" author="Weitz" date="2020-03-29" duration="30:31" id="2087" pubdate="2020-03-29" title="DD 2020-03-29 01 Crashkurs LaTeX-Syntax - mathematische Formeln online kommunizieren" url="http://mediathek.mt.haw-hamburg.de/video/DD-2020-03-29-01-Crashkurs-LaTeX-Syntax-mathematische-Formeln-online-kommunizieren/b478640efb4ea56018b3da584c42891e"><file type="mp4" url="http://mediathek.mt.haw-hamburg.de/getMedium/b478640efb4ea56018b3da584c42891e.mp4"/></video></layer><layer name="2020-04-04" dirName="2020-04-04" duration="36:17" videoCount="1"><video xmlns:xsi="http://www.w3.org/2001/XMLSchema-instance" author="Weitz" date="2020-04-04" duration="36:17" id="2089" pubdate="2020-04-04" title="DD 2020-04-04 01 Mehr &quot;Corona-Mathematik&quot;: Wie Epidemien modelliert werden" url="http://mediathek.mt.haw-hamburg.de/video/DD-2020-04-04-01-Mehr-quotCorona-Mathematikquot-Wie-Epidemien-modelliert-werden/290e7c5e2fd2e501d90f8a2037563316"><file type="mp4" url="http://mediathek.mt.haw-hamburg.de/getMedium/290e7c5e2fd2e501d90f8a2037563316.mp4"/></video></layer><layer name="2020-04-28" dirName="2020-04-28" duration="09:34" videoCount="1"><video xmlns:xsi="http://www.w3.org/2001/XMLSchema-instance" author="Weitz" date="2020-04-28" duration="09:34" id="2093" pubdate="2020-04-28" title="DD 2020-04-28 01 Worüber ich mich in Mathebüchern ärgere" url="http://mediathek.mt.haw-hamburg.de/video/DD-2020-04-28-01-Worueber-ich-mich-in-Mathebuechern-aergere/63eb70151b230e1de200337c4609284c"><file type="mp4" url="http://mediathek.mt.haw-hamburg.de/getMedium/63eb70151b230e1de200337c4609284c.mp4"/></video></layer><layer name="2020-05-10" dirName="2020-05-10" duration="1:08:02" videoCount="2"><video xmlns:xsi="http://www.w3.org/2001/XMLSchema-instance" author="Weitz" date="2020-05-10" duration="33:08" id="2094" pubdate="2020-05-10" title="DD 2020-05-10 01 Wie kommt der Zufall in den Computer? (Teil 1 von 2)" url="http://mediathek.mt.haw-hamburg.de/video/DD-2020-05-10-01-Wie-kommt-der-Zufall-in-den-Computer-Teil-1-von-2/c0f168066aa06bfd05432eac60418882"><file type="mp4" url="http://mediathek.mt.haw-hamburg.de/getMedium/c0f168066aa06bfd05432eac60418882.mp4"/></video><video xmlns:xsi="http://www.w3.org/2001/XMLSchema-instance" author="Weitz" date="2020-05-10" duration="34:54" id="2095" pubdate="2020-05-10" title="DD 2020-05-10 02 Wie kommt der Zufall in den Computer? (Teil 2 von 2)" url="http://mediathek.mt.haw-hamburg.de/video/DD-2020-05-10-02-Wie-kommt-der-Zufall-in-den-Computer-Teil-2-von-2/1e9c93e4c0a964b6c608263aa65d389b"><file type="mp4" url="http://mediathek.mt.haw-hamburg.de/getMedium/1e9c93e4c0a964b6c608263aa65d389b.mp4"/></video></layer><layer name="2020-05-23" dirName="2020-05-23" duration="40:47" videoCount="1"><video xmlns:xsi="http://www.w3.org/2001/XMLSchema-instance" author="Weitz" date="2020-05-23" duration="40:47" id="2096" pubdate="2020-05-23" title="DD 2020-05-23 01 Genau oder ungefähr?  Was ist numerische Mathematik?" url="http://mediathek.mt.haw-hamburg.de/video/DD-2020-05-23-01-Genau-oder-ungefaehr-Was-ist-numerische-Mathematik/c26b0265bd97ba46a36464e86b42e255"><file type="mp4" url="http://mediathek.mt.haw-hamburg.de/getMedium/c26b0265bd97ba46a36464e86b42e255.mp4"/></video></layer><layer name="2020-05-25" dirName="2020-05-25" duration="09:55" videoCount="1"><video xmlns:xsi="http://www.w3.org/2001/XMLSchema-instance" author="Weitz" date="2020-05-25" duration="09:55" id="2097" pubdate="2020-05-25" title="DD 2020-05-25 01 Wenn Zahlen zu genau sind..." url="http://mediathek.mt.haw-hamburg.de/video/DD-2020-05-25-01-Wenn-Zahlen-zu-genau-sind/cd604d66376257ae9729a671d02fc727"><file type="mp4" url="http://mediathek.mt.haw-hamburg.de/getMedium/cd604d66376257ae9729a671d02fc727.mp4"/></video></layer><layer name="2020-07-29" dirName="2020-07-29" duration="42:53" videoCount="1"><video xmlns:xsi="http://www.w3.org/2001/XMLSchema-instance" author="Weitz" date="2020-07-29" duration="42:53" id="2102" pubdate="2020-07-29" title="DD 2020-07-29 01 Wie man Computern das Ableiten beibringt oder: Warum Lisp?" url="http://mediathek.mt.haw-hamburg.de/video/DD-2020-07-29-01-Wie-man-Computern-das-Ableiten-beibringt-oder-Warum-Lisp/68ec1c72d9ce4d39cdee342cc257f288"><file type="mp4" url="http://mediathek.mt.haw-hamburg.de/getMedium/68ec1c72d9ce4d39cdee342cc257f288.mp4"/></video></layer><layer name="2020-09-21" dirName="2020-09-21" duration="10:36" videoCount="1"><video xmlns:xsi="http://www.w3.org/2001/XMLSchema-instance" author="Weitz" date="2020-09-21" duration="10:36" id="2105" pubdate="2020-09-21" title="DD 2020-09-21 01 Der Satz von Pick (&quot;physikalischer&quot; Beweis)" url="http://mediathek.mt.haw-hamburg.de/video/DD-2020-09-21-01-Der-Satz-von-Pick-quotphysikalischerquot-Beweis/d4cc45f521e412ee18116629d3d30e3a"><file type="mp4" url="http://mediathek.mt.haw-hamburg.de/getMedium/d4cc45f521e412ee18116629d3d30e3a.mp4"/></video></layer><layer name="2020-12-14" dirName="2020-12-14" duration="1:08:42" videoCount="1"><video xmlns:xsi="http://www.w3.org/2001/XMLSchema-instance" author="Weitz" date="2020-12-14" duration="1:08:42" id="2115" pubdate="2020-12-14" title="DD 2020-12-14 01 Die seltsamste Zahl: Chaitins Omega (Weihnachtsvideo 2020)" url="http://mediathek.mt.haw-hamburg.de/video/DD-2020-12-14-01-Die-seltsamste-Zahl-Chaitins-Omega-Weihnachtsvideo-2020/3e846dfd7b0871266cf98604c6cd30c1"><file type="mp4" url="http://mediathek.mt.haw-hamburg.de/getMedium/3e846dfd7b0871266cf98604c6cd30c1.mp4"/></video></layer><layer name="2020-12-27" dirName="2020-12-27" duration="1:18:49" videoCount="1"><video xmlns:xsi="http://www.w3.org/2001/XMLSchema-instance" author="Weitz" date="2020-12-27" duration="1:18:49" id="2116" pubdate="2020-12-28" title="DD 2020-12-27 01 Gödel (miss)verstehen - Was sagt der Unvollständigkeitssatz wirklich aus?" url="http://mediathek.mt.haw-hamburg.de/video/DD-2020-12-27-01-Goedel-missverstehen-Was-sagt-der-Unvollstaendigkeitssatz-wirklich-aus/2c30cb16dfac7d4b2a05ce1c0c9b86fd"><file type="mp4" url="http://mediathek.mt.haw-hamburg.de/getMedium/2c30cb16dfac7d4b2a05ce1c0c9b86fd.mp4"/></video></layer><layer name="2021-02-21" dirName="2021-02-21" duration="50:59" videoCount="1"><video xmlns:xsi="http://www.w3.org/2001/XMLSchema-instance" author="Weitz" date="2021-02-21" duration="50:59" id="2122" pubdate="2021-02-21" title="DD 2021-02-21 01 Beweise färben - Überzeugen, ohne etwas zu verraten" url="http://mediathek.mt.haw-hamburg.de/video/DD-2021-02-21-01-Beweise-faerben-Ueberzeugen-ohne-etwas-zu-verraten/1359b60243e515047b4fb9d6abf04714"><file type="mp4" url="http://mediathek.mt.haw-hamburg.de/getMedium/1359b60243e515047b4fb9d6abf04714.mp4"/></video></layer><layer name="2021-03-25" dirName="2021-03-25" duration="47:04" videoCount="1"><video xmlns:xsi="http://www.w3.org/2001/XMLSchema-instance" author="Weitz" date="2021-03-25" duration="47:04" id="2123" pubdate="2021-03-26" title="DD 2021-03-25 01 Ist 0,999... wirklich 1?  (Das Rätsel des Kontinuums)" url="http://mediathek.mt.haw-hamburg.de/video/DD-2021-03-25-01-Ist-0999-wirklich-1-Das-Raetsel-des-Kontinuums/ac826f859c04c83a6a6a6a598dd223f0"><file type="mp4" url="http://mediathek.mt.haw-hamburg.de/getMedium/ac826f859c04c83a6a6a6a598dd223f0.mp4"/></video></layer><layer name="2021-04-15" dirName="2021-04-15" duration="29:31" videoCount="1"><video xmlns:xsi="http://www.w3.org/2001/XMLSchema-instance" author="Weitz" date="2021-04-15" duration="29:31" id="2124" pubdate="2021-04-15" title="DD 2021-04-15 01 Wie viele Beweise braucht man?  (Der Satz des Theaitetos)" url="http://mediathek.mt.haw-hamburg.de/video/DD-2021-04-15-01-Wie-viele-Beweise-braucht-man-Der-Satz-des-Theaitetos/0a7d9cb51b36af8512c52d592df9015d"><file type="mp4" url="http://mediathek.mt.haw-hamburg.de/getMedium/0a7d9cb51b36af8512c52d592df9015d.mp4"/></video></layer><layer name="2021-05-15" dirName="2021-05-15" duration="1:22:23" videoCount="2"><video xmlns:xsi="http://www.w3.org/2001/XMLSchema-instance" author="Weitz" date="2021-05-15" duration="44:21" id="2125" pubdate="2021-05-16" title="DD 2021-05-15 01 Der längste Beweis aller Zeiten: Die Klassifikation der endlichen einfachen Gruppen (Teil 1 von 2)" url="http://mediathek.mt.haw-hamburg.de/video/DD-2021-05-15-01-Der-laengste-Beweis-aller-Zeiten-Die-Klassifikation-der-endlichen-einfachen-Gruppen-Teil-1-von-2/ad06df99580fee4bb779870acf505dd7"><file type="mp4" url="http://mediathek.mt.haw-hamburg.de/getMedium/ad06df99580fee4bb779870acf505dd7.mp4"/></video><video xmlns:xsi="http://www.w3.org/2001/XMLSchema-instance" author="Weitz" date="2021-05-15" duration="38:02" id="2126" pubdate="2021-05-16" title="DD 2021-05-15 02 Der längste Beweis aller Zeiten: Die Klassifikation der endlichen einfachen Gruppen (Teil 2 von 2)" url="http://mediathek.mt.haw-hamburg.de/video/DD-2021-05-15-02-Der-laengste-Beweis-aller-Zeiten-Die-Klassifikation-der-endlichen-einfachen-Gruppen-Teil-2-von-2/1086bdd481dee863f5a5dd54456d8d9d"><file type="mp4" url="http://mediathek.mt.haw-hamburg.de/getMedium/1086bdd481dee863f5a5dd54456d8d9d.mp4"/></video></layer><layer name="2021-07-19" dirName="2021-07-19" duration="22:14" videoCount="1"><video xmlns:xsi="http://www.w3.org/2001/XMLSchema-instance" author="Weitz" date="2021-07-19" duration="22:14" id="2129" pubdate="2021-07-19" title="DD 2021-07-19 01 Die einfachste Programmiersprache der Welt: FRACTRAN" url="http://mediathek.mt.haw-hamburg.de/video/DD-2021-07-19-01-Die-einfachste-Programmiersprache-der-Welt-FRACTRAN/26ce94878932f5eee4dc2d67e3a5fe2b"><file type="mp4" url="http://mediathek.mt.haw-hamburg.de/getMedium/26ce94878932f5eee4dc2d67e3a5fe2b.mp4"/></video></layer><layer name="2021-12-10" dirName="2021-12-10" duration="1:15:42" videoCount="1"><video xmlns:xsi="http://www.w3.org/2001/XMLSchema-instance" author="Weitz" date="2021-12-10" duration="1:15:42" id="2130" pubdate="2021-12-11" title="DD 2021-12-10 01 Mathematische Eleganz hoch drei (Weihnachtsvideo 2021)" url="http://mediathek.mt.haw-hamburg.de/video/DD-2021-12-10-01-Mathematische-Eleganz-hoch-drei-Weihnachtsvideo-2021/9e8bf4e0889384e2f159432a2d3a057e"><file type="mp4" url="http://mediathek.mt.haw-hamburg.de/getMedium/9e8bf4e0889384e2f159432a2d3a057e.mp4"/></video></layer><layer name="2022-04-09" dirName="2022-04-09" duration="59:26" videoCount="1"><video xmlns:xsi="http://www.w3.org/2001/XMLSchema-instance" author="Weitz" date="2022-04-09" duration="59:26" id="2138" pubdate="2022-04-10" title="DD 2022-04-09 01 Was ist lineare Algebra?  Und wofür braucht man Vektorräume?" url="http://mediathek.mt.haw-hamburg.de/video/DD-2022-04-09-01-Was-ist-lineare-Algebra-Und-wofuer-braucht-man-Vektorraeume/585c6582f4340fc8256902419fb9006d"><file type="mp4" url="http://mediathek.mt.haw-hamburg.de/getMedium/585c6582f4340fc8256902419fb9006d.mp4"/></video></layer><layer name="2022-05-05" dirName="2022-05-05" duration="39:14" videoCount="1"><video xmlns:xsi="http://www.w3.org/2001/XMLSchema-instance" author="Weitz" date="2022-05-05" duration="39:14" id="2140" pubdate="2022-05-05" title="DD 2022-05-05 01 Ist das Lehren von Mathematik Sisyphosarbeit?" url="http://mediathek.mt.haw-hamburg.de/video/DD-2022-05-05-01-Ist-das-Lehren-von-Mathematik-Sisyphosarbeit/86e786946da44ffcd6d69b9c101c6ecb"><file type="mp4" url="http://mediathek.mt.haw-hamburg.de/getMedium/86e786946da44ffcd6d69b9c101c6ecb.mp4"/></video></layer><layer name="2022-06-02" dirName="2022-06-02" duration="49:47" videoCount="1"><video xmlns:xsi="http://www.w3.org/2001/XMLSchema-instance" author="Weitz" date="2022-06-02" duration="49:47" id="2142" pubdate="2022-06-03" title="DD 2022-06-02 01 &quot;Dieser Satz ist merkwürdig!&quot;" url="http://mediathek.mt.haw-hamburg.de/video/DD-2022-06-02-01-quotDieser-Satz-ist-merkwuerdigquot/7effc9a7dcbd1dda1e77487ab0c26935"><file type="mp4" url="http://mediathek.mt.haw-hamburg.de/getMedium/7effc9a7dcbd1dda1e77487ab0c26935.mp4"/></video></layer><layer name="2022-07-05" dirName="2022-07-05" duration="19:54" videoCount="1"><video xmlns:xsi="http://www.w3.org/2001/XMLSchema-instance" author="Weitz" date="2022-07-05" duration="19:54" id="2144" pubdate="2022-07-05" title="DD 2022-07-05 01 Ein 2000 Jahre alter Brief und das Geheimnis von Archimedes" url="http://mediathek.mt.haw-hamburg.de/video/DD-2022-07-05-01-Ein-2000-Jahre-alter-Brief-und-das-Geheimnis-von-Archimedes/20cab2a04ec39e413894343a2e65245c"><file type="mp4" url="http://mediathek.mt.haw-hamburg.de/getMedium/20cab2a04ec39e413894343a2e65245c.mp4"/></video></layer><layer name="2022-08-20" dirName="2022-08-20" duration="52:36" videoCount="1"><video xmlns:xsi="http://www.w3.org/2001/XMLSchema-instance" author="Weitz" date="2022-08-20" duration="52:36" id="2147" pubdate="2022-08-21" title="DD 2022-08-20 01 Die schönsten Beweise der Riemannschen Vermutung (und noch mehr!)" url="http://mediathek.mt.haw-hamburg.de/video/DD-2022-08-20-01-Die-schoensten-Beweise-der-Riemannschen-Vermutung-und-noch-mehr/269685348f1d193d17310e0e2d041064"><file type="mp4" url="http://mediathek.mt.haw-hamburg.de/getMedium/269685348f1d193d17310e0e2d041064.mp4"/></video></layer><layer name="2022-12-22" dirName="2022-12-22" duration="2:27:02" videoCount="2"><video xmlns:xsi="http://www.w3.org/2001/XMLSchema-instance" author="Weitz" date="2022-12-22" duration="1:25:57" id="2153" pubdate="2022-12-23" title="DD 2022-12-22 01 Zahme Knoten und alte Zöpfe (Weihnachtsvorlesung 2022, Teil 1 von 2)" url="http://mediathek.mt.haw-hamburg.de/video/DD-2022-12-22-01-Zahme-Knoten-und-alte-Zoepfe-Weihnachtsvorlesung-2022-Teil-1-von-2/e499f2fcfb41b91f83aa1f6f086b7b33"><file type="mp4" url="http://mediathek.mt.haw-hamburg.de/getMedium/e499f2fcfb41b91f83aa1f6f086b7b33.mp4"/></video><video xmlns:xsi="http://www.w3.org/2001/XMLSchema-instance" author="Weitz" date="2022-12-22" duration="1:01:05" id="2154" pubdate="2022-12-23" title="DD 2022-12-22 02 Gelöste Knoten und ungelöste Probleme (Weihnachtsvorlesung 2022, Teil 1 von 2)" url="http://mediathek.mt.haw-hamburg.de/video/DD-2022-12-22-02-Geloeste-Knoten-und-ungeloeste-Probleme-Weihnachtsvorlesung-2022-Teil-1-von-2/ae0335bcb4d2001884df6fd8e700bc9a"><file type="mp4" url="http://mediathek.mt.haw-hamburg.de/getMedium/ae0335bcb4d2001884df6fd8e700bc9a.mp4"/></video></layer><layer name="2023-01-19" dirName="2023-01-19" duration="31:48" videoCount="1"><video xmlns:xsi="http://www.w3.org/2001/XMLSchema-instance" author="Weitz" date="2023-01-19" duration="31:48" id="2156" pubdate="2023-01-19" title="DD 2023-01-19 01 ChatGPT und die Mathematik" url="http://mediathek.mt.haw-hamburg.de/video/DD-2023-01-19-01-ChatGPT-und-die-Mathematik/471c51c32b8d3e0b7f7b1384d1b12bac"><file type="mp4" url="http://mediathek.mt.haw-hamburg.de/getMedium/471c51c32b8d3e0b7f7b1384d1b12bac.mp4"/></video></layer><layer name="2023-01-30" dirName="2023-01-30" duration="49:41" videoCount="1"><video xmlns:xsi="http://www.w3.org/2001/XMLSchema-instance" author="Weitz" date="2023-01-30" duration="49:41" id="2157" pubdate="2023-01-30" title="DD 2023-01-30 01 ChatGPT und die Logik" url="http://mediathek.mt.haw-hamburg.de/video/DD-2023-01-30-01-ChatGPT-und-die-Logik/470cc2034bafa407d3e422dd6a1b9cdf"><file type="mp4" url="http://mediathek.mt.haw-hamburg.de/getMedium/470cc2034bafa407d3e422dd6a1b9cdf.mp4"/></video></layer><layer name="2023-02-23" dirName="2023-02-23" duration="13:49" videoCount="1"><video xmlns:xsi="http://www.w3.org/2001/XMLSchema-instance" author="Weitz" date="2023-02-23" duration="13:49" id="2158" pubdate="2023-02-23" title="DD 2023-02-23 01 Wie man JEDEN Intelligenztest besteht: Das Geheimnis der Zahl 42" url="http://mediathek.mt.haw-hamburg.de/video/DD-2023-02-23-01-Wie-man-JEDEN-Intelligenztest-besteht-Das-Geheimnis-der-Zahl-42/a80ec959b26c5e75e75da11be7f43709"><file type="mp4" url="http://mediathek.mt.haw-hamburg.de/getMedium/a80ec959b26c5e75e75da11be7f43709.mp4"/></video></layer><layer name="2023-03-03" dirName="2023-03-03" duration="56:33" videoCount="1"><video xmlns:xsi="http://www.w3.org/2001/XMLSchema-instance" author="Weitz" date="2023-03-03" duration="56:33" id="2159" pubdate="2023-03-04" title="DD 2023-03-03 01 Der Große Satz von Fermat (mit Beweis für n=3 und n=4)" url="http://mediathek.mt.haw-hamburg.de/video/DD-2023-03-03-01-Der-Grosse-Satz-von-Fermat-mit-Beweis-fuer-n3-und-n4/48f3393dc732e086ec4b06036268963e"><file type="mp4" url="http://mediathek.mt.haw-hamburg.de/getMedium/48f3393dc732e086ec4b06036268963e.mp4"/></video></layer></layer></layer></indexer>